{"v":"5.12.1","fr":60,"ip":0,"op":60,"w":500,"h":500,"nm":"system-regular-128-cloud-done","ddd":0,"assets":[{"id":"comp_1","nm":"hover-cloud-done","fr":60,"layers":[{"ddd":0,"ind":1,"ty":4,"nm":".primary.design","cl":"primary design","sr":1,"ks":{"o":{"a":0,"k":100,"ix":11},"r":{"a":0,"k":0,"ix":10},"p":{"a":1,"k":[{"i":{"x":0.258,"y":1},"o":{"x":0.333,"y":0},"t":0,"s":[250.004,250.003,0],"to":[4.167,0,0],"ti":[0,0,0]},{"i":{"x":0.313,"y":1},"o":{"x":0.333,"y":0},"t":23,"s":[275.004,250.003,0],"to":[0,0,0],"ti":[4.167,0,0]},{"t":60,"s":[250.004,250.003,0]}],"ix":2,"l":2},"a":{"a":0,"k":[0,0,0],"ix":1,"l":2},"s":{"a":0,"k":[100,100,100],"ix":6,"l":2}},"ao":0,"shapes":[{"ty":"gr","it":[{"ind":0,"ty":"sh","ix":1,"ks":{"a":0,"k":{"i":[[0,-28.75],[52.709,-5.208],[3.541,0],[0,0],[0,46.041],[-14.999,15.001],[-6.667,3.75],[0,3.541],[-38.958,1.457],[-44.584,0],[-5,-58.749],[-7.917,-7.917]],"o":[[0,53.958],[-3.333,0.417],[0,0],[-46.042,0],[0,-23.125],[5.417,-5.417],[-0.624,-3.543],[0,-39.167],[18.542,-37.293],[60,0],[10.209,5.208],[18.958,18.751]],"v":[[192.709,46.875],[98.959,150.417],[88.542,151.042],[-109.376,151.042],[-192.709,67.709],[-168.334,8.75],[-150.21,-5],[-151.042,-15.625],[-81.042,-88.334],[20.833,-151.042],[134.792,-46.459],[162.085,-26.667]],"c":true},"ix":2},"nm":"Path 1","mn":"ADBE Vector Shape - Group","hd":false},{"ty":"st","c":{"a":0,"k":[0.071,0.075,0.192,1],"ix":3,"x":"var $bm_rt;\n$bm_rt = comp('system-regular-128-cloud-done').layer('control').effect('primary')('Color');"},"o":{"a":0,"k":100,"ix":4},"w":{"a":0,"k":31.3,"ix":5},"lc":2,"lj":2,"bm":0,"nm":".primary","mn":"ADBE Vector Graphic - Stroke","hd":false,"cl":"primary"},{"ty":"tr","p":{"a":0,"k":[0,0],"ix":2},"a":{"a":0,"k":[0,0],"ix":1},"s":{"a":0,"k":[100,100],"ix":3},"r":{"a":0,"k":0,"ix":6},"o":{"a":0,"k":100,"ix":7},"sk":{"a":0,"k":0,"ix":4},"sa":{"a":0,"k":0,"ix":5},"nm":"Transform"}],"nm":"Group 1","np":2,"cix":2,"bm":0,"ix":1,"mn":"ADBE Vector Group","hd":false}],"ip":1,"op":60,"st":0,"ct":1,"bm":0},{"ddd":0,"ind":2,"ty":4,"nm":".primary.design","cl":"primary design","parent":1,"sr":1,"ks":{"o":{"a":0,"k":100,"ix":11},"r":{"a":0,"k":0,"ix":10},"p":{"a":0,"k":[0,0,0],"ix":2,"l":2},"a":{"a":0,"k":[250.004,250.003,0],"ix":1,"l":2},"s":{"a":0,"k":[100,100,100],"ix":6,"l":2}},"ao":0,"shapes":[{"ty":"gr","it":[{"ind":0,"ty":"sh","ix":1,"ks":{"a":0,"k":{"i":[[0,0],[0,0],[0,0]],"o":[[0,0],[0,0],[0,0]],"v":[[114.695,-93.473],[-22.139,41.667],[-62.5,1.931]],"c":false},"ix":2},"nm":"Path 1","mn":"ADBE Vector Shape - Group","hd":false},{"ty":"st","c":{"a":0,"k":[0.071,0.075,0.192,1],"ix":3,"x":"var $bm_rt;\n$bm_rt = comp('system-regular-128-cloud-done').layer('control').effect('primary')('Color');"},"o":{"a":0,"k":100,"ix":4},"w":{"a":0,"k":31.3,"ix":5},"lc":2,"lj":2,"bm":0,"nm":".primary","mn":"ADBE Vector Graphic - Stroke","hd":false,"cl":"primary"},{"ty":"tm","s":{"a":1,"k":[{"i":{"x":[0.833],"y":[1]},"o":{"x":[0.333],"y":[0]},"t":1,"s":[100]},{"t":20,"s":[100],"h":1},{"i":{"x":[0.19],"y":[1]},"o":{"x":[0.167],"y":[0.167]},"t":28,"s":[0]},{"t":60,"s":[100]}],"ix":1},"e":{"a":1,"k":[{"i":{"x":[0.833],"y":[0.833]},"o":{"x":[0.333],"y":[0]},"t":1,"s":[29.4]},{"t":20,"s":[100],"h":1},{"i":{"x":[0.19],"y":[1]},"o":{"x":[0.167],"y":[0.167]},"t":28,"s":[0]},{"t":60,"s":[29.4]}],"ix":2},"o":{"a":0,"k":0,"ix":3},"m":1,"ix":3,"nm":"Trim Paths 1","mn":"ADBE Vector Filter - Trim","hd":false},{"ty":"tr","p":{"a":0,"k":[260.42,276.045],"ix":2},"a":{"a":0,"k":[0,0],"ix":1},"s":{"a":0,"k":[100,100],"ix":3},"r":{"a":0,"k":0,"ix":6},"o":{"a":0,"k":100,"ix":7},"sk":{"a":0,"k":0,"ix":4},"sa":{"a":0,"k":0,"ix":5},"nm":"Transform"}],"nm":"Group 1","np":3,"cix":2,"bm":0,"ix":1,"mn":"ADBE Vector Group","hd":false}],"ip":1,"op":60,"st":0,"ct":1,"bm":0},{"ddd":0,"ind":3,"ty":4,"nm":".primary.design","cl":"primary design","sr":1,"ks":{"o":{"a":0,"k":100,"ix":11},"r":{"a":0,"k":0,"ix":10},"p":{"a":0,"k":[250.003,250.003,0],"ix":2,"l":2},"a":{"a":0,"k":[250.003,250.003,0],"ix":1,"l":2},"s":{"a":0,"k":[100,100,100],"ix":6,"l":2}},"ao":0,"shapes":[{"ty":"gr","it":[{"ind":0,"ty":"sh","ix":1,"ks":{"a":0,"k":{"i":[[3.967,0],[3.046,2.999],[0,0],[-6.063,6.159],[-6.159,-6.063],[0,0],[0,0],[-6.064,-6.158],[6.159,-6.064],[0,0]],"o":[[-3.967,0],[0,0],[-6.159,-6.064],[6.063,-6.159],[0,0],[0,0],[6.16,-6.064],[6.063,6.159],[0,0],[-3.045,2.999]],"v":[[-22.139,57.317],[-33.119,52.819],[-73.48,13.083],[-73.653,-9.049],[-51.521,-9.222],[-22.139,19.705],[51.521,-52.819],[73.653,-52.647],[73.48,-30.515],[-11.16,52.819]],"c":true},"ix":2},"nm":"Path 1","mn":"ADBE Vector Shape - Group","hd":false},{"ty":"fl","c":{"a":0,"k":[0.071,0.075,0.192,1],"ix":4,"x":"var $bm_rt;\n$bm_rt = comp('system-regular-128-cloud-done').layer('control').effect('primary')('Color');"},"o":{"a":0,"k":100,"ix":5},"r":1,"bm":0,"nm":".primary","mn":"ADBE Vector Graphic - Fill","hd":false,"cl":"primary"},{"ty":"tr","p":{"a":0,"k":[260.42,276.045],"ix":2},"a":{"a":0,"k":[0,0],"ix":1},"s":{"a":0,"k":[100,100],"ix":3},"r":{"a":0,"k":0,"ix":6},"o":{"a":0,"k":100,"ix":7},"sk":{"a":0,"k":0,"ix":4},"sa":{"a":0,"k":0,"ix":5},"nm":"Transform"}],"nm":"Group 1","np":2,"cix":2,"bm":0,"ix":1,"mn":"ADBE Vector Group","hd":false},{"ty":"gr","it":[{"ty":"gr","it":[{"ind":0,"ty":"sh","ix":1,"ks":{"a":0,"k":{"i":[[51.698,0],[16.569,-33.325],[5.727,-0.214],[0,-30.849],[-0.407,-2.308],[5.79,-3.256],[4.383,-4.383],[0,-18.12],[-37.321,0],[0,0],[-0.98,0.097],[0,45.663],[16.753,16.57],[8.698,4.438],[0.459,5.387]],"o":[[-37.626,0],[-2.552,5.131],[-30.805,1.152],[0,3.089],[1.152,6.542],[-5.392,3.032],[-12.763,12.763],[0,37.321],[0,0],[0.916,-0.267],[45.402,-4.486],[0,-23.679],[-6.849,-6.849],[-4.816,-2.457],[-4.378,-51.457]],"v":[[20.833,-135.393],[-67.029,-81.366],[-80.458,-72.694],[-135.392,-15.625],[-134.796,-7.714],[-142.538,8.641],[-157.268,19.816],[-177.059,67.709],[-109.375,135.393],[94.571,135.393],[97.419,134.843],[177.059,46.875],[151.08,-15.541],[127.68,-32.519],[119.198,-45.132]],"c":true},"ix":2},"nm":"Path 1","mn":"ADBE Vector Shape - Group","hd":false},{"ind":1,"ty":"sh","ix":2,"ks":{"a":0,"k":{"i":[[2.173,0],[0,0],[0,54.58],[-18.675,18.676],[-4.534,3.218],[0,0.865],[-15.977,16.569],[-19.422,2.749],[-17.604,11.032],[-24.522,0],[-24.035,-22.191],[-4.405,-29.156],[-7.112,-7.113],[0,-32.105],[20.114,-22.073],[27.689,-3.816]],"o":[[0,0],[-54.58,0],[0,-26.48],[3.944,-3.944],[-0.021,-0.834],[0,-22.998],[13.806,-14.318],[10.42,-17.725],[20.627,-12.926],[32.854,0],[21.798,20.125],[8.685,5.203],[22.683,22.435],[0,29.898],[-18.944,20.789],[-1.881,0.8]],"v":[[98.957,166.692],[-109.375,166.692],[-208.36,67.709],[-179.401,-2.315],[-166.66,-13.078],[-166.693,-15.625],[-141.917,-76.983],[-90.801,-103.155],[-48.18,-146.934],[20.834,-166.692],[109.054,-132.28],[149.386,-56.257],[173.151,-37.733],[208.36,46.876],[177.167,127.468],[105.08,165.449]],"c":true},"ix":2},"nm":"Path 2","mn":"ADBE Vector Shape - Group","hd":false},{"ty":"fl","c":{"a":0,"k":[0.071,0.075,0.192,1],"ix":4,"x":"var $bm_rt;\n$bm_rt = comp('system-regular-128-cloud-done').layer('control').effect('primary')('Color');"},"o":{"a":0,"k":100,"ix":5},"r":1,"bm":0,"nm":".primary","mn":"ADBE Vector Graphic - Fill","hd":false,"cl":"primary"},{"ty":"tr","p":{"a":0,"k":[0,0],"ix":2},"a":{"a":0,"k":[0,0],"ix":1},"s":{"a":0,"k":[100,100],"ix":3},"r":{"a":0,"k":0,"ix":6},"o":{"a":0,"k":100,"ix":7},"sk":{"a":0,"k":0,"ix":4},"sa":{"a":0,"k":0,"ix":5},"nm":"Transform"}],"nm":"Group 1","np":3,"cix":2,"bm":0,"ix":1,"mn":"ADBE Vector Group","hd":false},{"ty":"tr","p":{"a":0,"k":[250.003,250.003],"ix":2},"a":{"a":0,"k":[0,0],"ix":1},"s":{"a":0,"k":[100,100],"ix":3},"r":{"a":0,"k":0,"ix":6},"o":{"a":0,"k":100,"ix":7},"sk":{"a":0,"k":0,"ix":4},"sa":{"a":0,"k":0,"ix":5},"nm":"Transform"}],"nm":"Group 2","np":1,"cix":2,"bm":0,"ix":2,"mn":"ADBE Vector Group","hd":false}],"ip":60,"op":300,"st":0,"ct":1,"bm":0},{"ddd":0,"ind":4,"ty":4,"nm":".primary.design","cl":"primary design","sr":1,"ks":{"o":{"a":0,"k":100,"ix":11},"r":{"a":0,"k":0,"ix":10},"p":{"a":0,"k":[250.003,250.003,0],"ix":2,"l":2},"a":{"a":0,"k":[250.003,250.003,0],"ix":1,"l":2},"s":{"a":0,"k":[100,100,100],"ix":6,"l":2}},"ao":0,"shapes":[{"ty":"gr","it":[{"ind":0,"ty":"sh","ix":1,"ks":{"a":0,"k":{"i":[[3.967,0],[3.046,2.999],[0,0],[-6.063,6.159],[-6.159,-6.063],[0,0],[0,0],[-6.064,-6.158],[6.159,-6.064],[0,0]],"o":[[-3.967,0],[0,0],[-6.159,-6.064],[6.063,-6.159],[0,0],[0,0],[6.16,-6.064],[6.063,6.159],[0,0],[-3.045,2.999]],"v":[[-22.139,57.317],[-33.119,52.819],[-73.48,13.083],[-73.653,-9.049],[-51.521,-9.222],[-22.139,19.705],[51.521,-52.819],[73.653,-52.647],[73.48,-30.515],[-11.16,52.819]],"c":true},"ix":2},"nm":"Path 1","mn":"ADBE Vector Shape - Group","hd":false},{"ty":"fl","c":{"a":0,"k":[0.071,0.075,0.192,1],"ix":4,"x":"var $bm_rt;\n$bm_rt = comp('system-regular-128-cloud-done').layer('control').effect('primary')('Color');"},"o":{"a":0,"k":100,"ix":5},"r":1,"bm":0,"nm":".primary","mn":"ADBE Vector Graphic - Fill","hd":false,"cl":"primary"},{"ty":"tr","p":{"a":0,"k":[260.42,276.045],"ix":2},"a":{"a":0,"k":[0,0],"ix":1},"s":{"a":0,"k":[100,100],"ix":3},"r":{"a":0,"k":0,"ix":6},"o":{"a":0,"k":100,"ix":7},"sk":{"a":0,"k":0,"ix":4},"sa":{"a":0,"k":0,"ix":5},"nm":"Transform"}],"nm":"Group 1","np":2,"cix":2,"bm":0,"ix":1,"mn":"ADBE Vector Group","hd":false},{"ty":"gr","it":[{"ty":"gr","it":[{"ind":0,"ty":"sh","ix":1,"ks":{"a":0,"k":{"i":[[51.698,0],[16.569,-33.325],[5.727,-0.214],[0,-30.849],[-0.407,-2.308],[5.79,-3.256],[4.383,-4.383],[0,-18.12],[-37.321,0],[0,0],[-0.98,0.097],[0,45.663],[16.753,16.57],[8.698,4.438],[0.459,5.387]],"o":[[-37.626,0],[-2.552,5.131],[-30.805,1.152],[0,3.089],[1.152,6.542],[-5.392,3.032],[-12.763,12.763],[0,37.321],[0,0],[0.916,-0.267],[45.402,-4.486],[0,-23.679],[-6.849,-6.849],[-4.816,-2.457],[-4.378,-51.457]],"v":[[20.833,-135.393],[-67.029,-81.366],[-80.458,-72.694],[-135.392,-15.625],[-134.796,-7.714],[-142.538,8.641],[-157.268,19.816],[-177.059,67.709],[-109.375,135.393],[94.571,135.393],[97.419,134.843],[177.059,46.875],[151.08,-15.541],[127.68,-32.519],[119.198,-45.132]],"c":true},"ix":2},"nm":"Path 1","mn":"ADBE Vector Shape - Group","hd":false},{"ind":1,"ty":"sh","ix":2,"ks":{"a":0,"k":{"i":[[2.173,0],[0,0],[0,54.58],[-18.675,18.676],[-4.534,3.218],[0,0.865],[-15.977,16.569],[-19.422,2.749],[-17.604,11.032],[-24.522,0],[-24.035,-22.191],[-4.405,-29.156],[-7.112,-7.113],[0,-32.105],[20.114,-22.073],[27.689,-3.816]],"o":[[0,0],[-54.58,0],[0,-26.48],[3.944,-3.944],[-0.021,-0.834],[0,-22.998],[13.806,-14.318],[10.42,-17.725],[20.627,-12.926],[32.854,0],[21.798,20.125],[8.685,5.203],[22.683,22.435],[0,29.898],[-18.944,20.789],[-1.881,0.8]],"v":[[98.957,166.692],[-109.375,166.692],[-208.36,67.709],[-179.401,-2.315],[-166.66,-13.078],[-166.693,-15.625],[-141.917,-76.983],[-90.801,-103.155],[-48.18,-146.934],[20.834,-166.692],[109.054,-132.28],[149.386,-56.257],[173.151,-37.733],[208.36,46.876],[177.167,127.468],[105.08,165.449]],"c":true},"ix":2},"nm":"Path 2","mn":"ADBE Vector Shape - Group","hd":false},{"ty":"fl","c":{"a":0,"k":[0.071,0.075,0.192,1],"ix":4,"x":"var $bm_rt;\n$bm_rt = comp('system-regular-128-cloud-done').layer('control').effect('primary')('Color');"},"o":{"a":0,"k":100,"ix":5},"r":1,"bm":0,"nm":".primary","mn":"ADBE Vector Graphic - Fill","hd":false,"cl":"primary"},{"ty":"tr","p":{"a":0,"k":[0,0],"ix":2},"a":{"a":0,"k":[0,0],"ix":1},"s":{"a":0,"k":[100,100],"ix":3},"r":{"a":0,"k":0,"ix":6},"o":{"a":0,"k":100,"ix":7},"sk":{"a":0,"k":0,"ix":4},"sa":{"a":0,"k":0,"ix":5},"nm":"Transform"}],"nm":"Group 1","np":3,"cix":2,"bm":0,"ix":1,"mn":"ADBE Vector Group","hd":false},{"ty":"tr","p":{"a":0,"k":[250.003,250.003],"ix":2},"a":{"a":0,"k":[0,0],"ix":1},"s":{"a":0,"k":[100,100],"ix":3},"r":{"a":0,"k":0,"ix":6},"o":{"a":0,"k":100,"ix":7},"sk":{"a":0,"k":0,"ix":4},"sa":{"a":0,"k":0,"ix":5},"nm":"Transform"}],"nm":"Group 2","np":1,"cix":2,"bm":0,"ix":2,"mn":"ADBE Vector Group","hd":false}],"ip":0,"op":1,"st":0,"ct":1,"bm":0}]}],"layers":[{"ddd":0,"ind":1,"ty":3,"nm":"control","sr":1,"ks":{"o":{"a":0,"k":0,"ix":11},"r":{"a":0,"k":0,"ix":10},"p":{"a":0,"k":[0,0],"ix":2,"l":2},"a":{"a":0,"k":[0,0,0],"ix":1,"l":2},"s":{"a":0,"k":[100,100,100],"ix":6,"l":2}},"ao":0,"ef":[{"ty":5,"nm":"primary","np":3,"mn":"ADBE Color Control","ix":1,"en":1,"ef":[{"ty":2,"nm":"Color","mn":"ADBE Color Control-0001","ix":1,"v":{"a":0,"k":[0.071,0.075,0.192],"ix":1}}]}],"ip":0,"op":131,"st":0,"bm":0},{"ddd":0,"ind":3,"ty":0,"nm":"hover-cloud-done","refId":"comp_1","sr":1,"ks":{"o":{"a":0,"k":100,"ix":11},"r":{"a":0,"k":0,"ix":10},"p":{"a":0,"k":[250,250,0],"ix":2,"l":2},"a":{"a":0,"k":[250,250,0],"ix":1,"l":2},"s":{"a":0,"k":[100,100,100],"ix":6,"l":2}},"ao":0,"w":500,"h":500,"ip":0,"op":70,"st":0,"bm":0}],"markers":[{"tm":0,"cm":"default:hover-cloud-done","dr":60}],"props":{}}